torchmers/__init__.py
torchmers/constants.py
torchmers/counting.py
torchmers/modules.py
torchmers/tokenizers.py
torchmers/utils.py
torchmers-0.1.0.dist-info/METADATA
torchmers-0.1.0.dist-info/WHEEL
torchmers-0.1.0.dist-info/RECORD
