Metadata-Version: 2.1
Name: torchmers
Version: 0.1.0
Summary: 
Author: Kristian Klemon
Author-email: kristian.klemon@gmail.com
Requires-Python: >=3.10,<3.11
Classifier: Programming Language :: Python :: 3
Classifier: Programming Language :: Python :: 3.10
Requires-Dist: numpy (>=1.26.0,<2.0.0)
Requires-Dist: torch (>=2.0.1,<3.0.0)
